{
  "person": "Mate",
  "this person": "Mate",
  "guy": "Mate",
  "cellmate": "Mate",
  "cell mate": "Mate",
  "inmate": "Mate",
  "partner": "Mate",
  "criminal": "Mate",
  "guard": "Prison Guard",
  "prisonguard": "Prison Guard",
  "warden": "Prison Guard",
  "correctional officer": "Prison Guard",
  "jailor": "Prison Guard",
  "prison officer": "Prison Guard",
  "detention officer": "Prison Guard",
  "custodial officer": "Prison Guard",
  "correctional staff": "Prison Guard",
  "correctional agent": "Prison Guard",
  "correctional employee": "Prison Guard",
  "correctional deputy": "Prison Guard",
  "corrections officer": "Prison Guard",
  "prison warden": "Prison Guard",
  "prison keeper": "Prison Guard",
  "jail superintendent": "Prison Guard",
  "detention center guard": "Prison Guard",
  "penitentiary warden": "Prison Guard",
  "prison watchman": "Prison Guard",
  "jail sentinel": "Prison Guard",
  "jail guard": "Prison Guard",
  "penitentiary guard": "Prison Guard",
  "custodian": "Janitor",
  "cleaner": "Janitor",
  "caretaker": "Janitor",
  "housekeeper": "Janitor",
  "attendant": "Janitor",
  "steward": "Janitor",
  "sweeper": "Janitor",
  "maintenance worker": "Janitor",
  "house cleaner": "Janitor",
  "sanitation engineer": "Janitor",
  "building superintendent": "Janitor",
  "facility manager": "Janitor",
  "groundskeeper": "Janitor",
  "maid": "Janitor",
  "porter": "Janitor",
  "housemaid": "Janitor",
  "handyman": "Janitor",
  "groundsman": "Janitor",
  "house steward": "Janitor",
  "service technician": "Janitor",
  "janitor": "Janitor",
  "jnatior": "Janitor",
  "aviator": "Pilot",
  "pilot": "Pilot",
  "flyer": "Pilot",
  "captain": "Pilot",
  "airman": "Pilot",
  "navigator": "Pilot",
  "aerialist": "Pilot",
  "aircrew": "Pilot",
  "helmsman": "Pilot",
  "wingman": "Pilot",
  "flight officer": "Pilot",
  "sky jockey": "Pilot",
  "ace": "Pilot",
  "cockpit operator": "Pilot",
  "jet jockey": "Pilot",
  "airmaster": "Pilot",
  "infirmary": "Infirmary",
  "infermary": "Infirmary",
  "infirmery": "Infirmary",
  "kitchen": "Kitchen",
  "kichen": "Kitchen",
  "office": "office",
  "helipad": "Heli Pad",
  "helistop": "Heli Pad",
  "landing pad": "Heli Pad",
  "helicopter": "Heli Pad",
  "laundry": "Laundry room",
  "landry room": "Laundry room",
  "pepper": "Cayenne Pepper",
  "cayenne": "Cayenne Pepper",
  "paprica": "Cayenne Pepper",
  "caynne": "Cayenne Pepper",
  "sunflower": "Sunflower",
  "sun": "Sunflower",
  "flower": "Sunflower",
  "bioluminescent algae": "Bioluminescent Algae",
  "bioluminescent": "Bioluminescent Algae",
  "algae": "Bioluminescent Algae",
  "lavender": "Lavender",
  "dirty clothes basket": "clothes basket",
  "basket": "clothes basket",
  "clothes": "clothes basket",
  "locker": "lockers",
  "lockers": "lockers",
  "washingmachines": "washing machines",
  "washing machine": "washing machines",
  "wash machine": "washing machines",
  "broccoli": "Broccoli",
  "brocoli": "Broccoli",
  "brokoli": "Broccoli",
  "eat": "eat",
  "drug": "drug",
  "cabine": "cabinet",
  "cabinet": "cabinet",
  "cabinets": "cabinet",
  "lamp": "lamp",
  "lamps": "lamp",
  "telefone": "telephone",
  "telephone": "telephone",
  "phone": "telephone",
  "chair": "chair",
  "chairs": "chair",
  "son": "Son",
  "friend": "Friend",
  "stefan": "Friend",
  "stephan": "Friend",
  "array": "Array",
  "arrays": "Array",
  "list": "List",
  "lists": "List",
  "variable": "Variable",
  "variabel": "Variable",
  "variables": "Variable",
  "queue": "Queue",
  "queues": "Queue",
  "abandon": "Abandon",
  "reject": "Abandon",
  "confront": "Confront",
  "confrontation": "Confront",
  "con": "Confront",
  "agree": "Agree"
}