[
  {
    "tag_name": "entity",
    "ids_to_tags": {
      "1": "B-all",
      "2": "I-all",
      "3": "L-all",
      "4": "U-all",
      "5": "B-answer_to_son",
      "6": "I-answer_to_son",
      "7": "L-answer_to_son",
      "8": "U-answer_to_son",
      "9": "B-called_person",
      "10": "I-called_person",
      "11": "L-called_person",
      "12": "U-called_person",
      "13": "B-deal_M",
      "14": "I-deal_M",
      "15": "L-deal_M",
      "16": "U-deal_M",
      "17": "B-dealwithfood",
      "18": "I-dealwithfood",
      "19": "L-dealwithfood",
      "20": "U-dealwithfood",
      "21": "B-ingredients",
      "22": "I-ingredients",
      "23": "L-ingredients",
      "24": "U-ingredients",
      "25": "B-items_in_Laundry_room",
      "26": "I-items_in_Laundry_room",
      "27": "L-items_in_Laundry_room",
      "28": "U-items_in_Laundry_room",
      "29": "B-items_in_office",
      "30": "I-items_in_office",
      "31": "L-items_in_office",
      "32": "U-items_in_office",
      "33": "B-locations",
      "34": "I-locations",
      "35": "L-locations",
      "36": "U-locations",
      "37": "B-numbercode",
      "38": "I-numbercode",
      "39": "L-numbercode",
      "40": "U-numbercode",
      "41": "B-person",
      "42": "I-person",
      "43": "L-person",
      "44": "U-person",
      "45": "B-profession",
      "46": "I-profession",
      "47": "L-profession",
      "48": "U-profession",
      "49": "B-vegetables",
      "50": "I-vegetables",
      "51": "L-vegetables",
      "52": "U-vegetables",
      "0": "O"
    },
    "tags_to_ids": {
      "B-all": 1,
      "I-all": 2,
      "L-all": 3,
      "U-all": 4,
      "B-answer_to_son": 5,
      "I-answer_to_son": 6,
      "L-answer_to_son": 7,
      "U-answer_to_son": 8,
      "B-called_person": 9,
      "I-called_person": 10,
      "L-called_person": 11,
      "U-called_person": 12,
      "B-deal_M": 13,
      "I-deal_M": 14,
      "L-deal_M": 15,
      "U-deal_M": 16,
      "B-dealwithfood": 17,
      "I-dealwithfood": 18,
      "L-dealwithfood": 19,
      "U-dealwithfood": 20,
      "B-ingredients": 21,
      "I-ingredients": 22,
      "L-ingredients": 23,
      "U-ingredients": 24,
      "B-items_in_Laundry_room": 25,
      "I-items_in_Laundry_room": 26,
      "L-items_in_Laundry_room": 27,
      "U-items_in_Laundry_room": 28,
      "B-items_in_office": 29,
      "I-items_in_office": 30,
      "L-items_in_office": 31,
      "U-items_in_office": 32,
      "B-locations": 33,
      "I-locations": 34,
      "L-locations": 35,
      "U-locations": 36,
      "B-numbercode": 37,
      "I-numbercode": 38,
      "L-numbercode": 39,
      "U-numbercode": 40,
      "B-person": 41,
      "I-person": 42,
      "L-person": 43,
      "U-person": 44,
      "B-profession": 45,
      "I-profession": 46,
      "L-profession": 47,
      "U-profession": 48,
      "B-vegetables": 49,
      "I-vegetables": 50,
      "L-vegetables": 51,
      "U-vegetables": 52,
      "O": 0
    },
    "num_tags": 53
  }
]